[
  {
    "type": "container",
    "title": "Registry",
    "description": "Docker image registry",
    "categories": ["docker"],
    "platform": "linux",
    "logo": "https://cloudinovasi.id/assets/img/logos/registry.png",
    "image": "registry:latest",
    "ports": [
      "5000/tcp"
    ],
    "volumes": ["/var/lib/registry"]
  },

  {
    "type": "container",
    "title": "Teamportal versione 6",
    "description": "Teamportal versione 6 creata da Nicola Marco Decandia",
    "categories": ["teamportal"],
    "platform": "linux",
    "logo": "http://www.seusweb.it//img/teamsystem.jpg",
    "image": "hermedia/teamportal:v6"
  },



  {
    "type": "container",
    "title": "Teamportal versione 5",
    "description": "Teamportal versione 6 creata da Nicola Marco Decandia",
    "categories": ["teamportal"],
    "platform": "linux",
    "logo": "http://www.seusweb.it//img/teamsystem.jpg",
    "image": "hermedia/teamportal:v5"
  },

  {
    "type": "container",
    "title": "Nginx",
    "description": "High performance web server",
    "categories": ["webserver"],
    "platform": "linux",
    "logo": "https://cloudinovasi.id/assets/img/logos/nginx.png",
    "image": "nginx:latest",
    "ports": [
      "80/tcp",
      "443/tcp"
    ],
    "volumes": ["/etc/nginx", "/usr/share/nginx/html"]
  }
]
